h5_to_ply/__init__.py
h5_to_ply/main.py
h5_to_ply-0.1.0.dist-info/METADATA
h5_to_ply-0.1.0.dist-info/WHEEL
h5_to_ply-0.1.0.dist-info/top_level.txt
h5_to_ply-0.1.0.dist-info/RECORD
