Metadata-Version: 2.1
Name: h5_to_ply
Version: 0.1.0
Summary: Converts Gaussians Splats from HDF5 to PLY format
Author-email: Ruben Hohndorf <ruben.hohndorf@gmail.com>
Project-URL: Homepage, https://github.com/404-Repo/h5_to_ply
Project-URL: Issues, https://github.com/404-Repo/h5_to_ply/issues
Classifier: Programming Language :: Python :: 3
Classifier: License :: OSI Approved :: MIT License
Classifier: Operating System :: OS Independent
Requires-Python: >=3.10
Requires-Dist: numpy ==1.26.4
Requires-Dist: h5py ==3.10.0
Requires-Dist: plyfile ==1.0.3
